{
  "identifiers": {
    "strategy": "SimpleRSIStrategy",
    "coin": "ENA",
    "timeframe": "15m",
    "start_date": "2024-04-02",
    "end_date": "2025-11-10"
  },
  "capital": {
    "initial": 10000,
    "final": 8030.03
  },
  "returns": {
    "total_return": -1969.97,
    "total_return_pct": -19.7,
    "annualized_return": -12.75,
    "cagr": -12.75
  },
  "risk": {
    "sharpe_ratio": -2.965,
    "sortino_ratio": -2.045,
    "calmar_ratio": -0.636,
    "max_drawdown": 0.2003,
    "max_drawdown_duration_days": 578.7,
    "volatility": 0.0622
  },
  "trades": {
    "total": 587,
    "winners": 245,
    "losers": 342,
    "win_rate": 41.74,
    "profit_factor": 0.734,
    "avg_win": 25.03,
    "avg_loss": -24.44,
    "largest_win": 119.96,
    "largest_loss": -75.65,
    "expectancy": -3.7927
  },
  "advanced": {
    "var_95": 0.0004,
    "cvar_95": 0.0009,
    "tail_ratio": 0.925,
    "avg_duration_hours": 5.23,
    "max_consecutive_wins": 7,
    "max_consecutive_losses": 12
  },
  "targets": {
    "sharpe_target_1.0": 